ensmallen_graph-0.5.2.dist-info/METADATA
ensmallen_graph-0.5.2.dist-info/WHEEL
ensmallen_graph/automatic_graphs.py
ensmallen_graph/automatic_graph_retrieval.py
ensmallen_graph/__init__.py
ensmallen_graph/__pycache__/__init__.cpython-37.pyc
ensmallen_graph/__pycache__/automatic_graphs.cpython-37.pyc
ensmallen_graph/graphs.json
ensmallen_graph/ensmallen_graph.cpython-39-darwin.so
ensmallen_graph-0.5.2.dist-info/RECORD
