Metadata-Version: 2.1
Name: ensmallen_graph
Version: 0.5.2
Requires-Dist: toml~=0.10.0
Requires-Dist: downloaders
Requires-Dist: compress_json
Keywords: python rust graph random walk
Author: Luca Cappelletti <cappelletti.luca94@gmail.com>, Tommaso Fontana <tommaso.fontana.96@gmail.com>
Author-Email: Luca Cappelletti <cappelletti.luca94@gmail.com>, Tommaso Fontana <tommaso.fontana.96@gmail.com>
License: MIT
Requires-Python: >=3.5
